cpuset/__init__.py
cpuset/config.py
cpuset/cset.py
cpuset/main.py
cpuset/util.py
cpuset/version.py
cpuset/commands/__init__.py
cpuset/commands/common.py
cpuset/commands/mem.py
cpuset/commands/proc.py
cpuset/commands/set.py
cpuset/commands/shield.py
cpuset_py3-1.0.2.dist-info/AUTHORS
cpuset_py3-1.0.2.dist-info/COPYING
cpuset_py3-1.0.2.dist-info/METADATA
cpuset_py3-1.0.2.dist-info/WHEEL
cpuset_py3-1.0.2.dist-info/entry_points.txt
cpuset_py3-1.0.2.dist-info/top_level.txt
cpuset_py3-1.0.2.dist-info/RECORD
