Metadata-Version: 2.1
Name: cpuset-py3
Version: 1.0.2
Summary: Fork of cpuset (https://github.com/lpechacek/cpuset) by Alex Tsariounov that works with python3
Home-page: https://github.com/parttimenerd/cpuset
Author: Johannes Bechberger
Author-email: UNKNOWN
License: UNKNOWN
Platform: UNKNOWN
Classifier: Programming Language :: Python :: 3 :: Only
